{"document": {"filename": "1072_341_0", "title": "341_0", "lines_and_colors": [[["We", "dont", "cry", "-", "Tim", "and", "I", "-"], {"1": "70", "2": "36", "4": "56"}], [["We", "are", "far", "too", "grand", "-"], {"4": "70"}], [["But", "we", "bolt", "the", "door", "tight"], {"2": "56", "4": "61", "5": "56"}], [["To", "prevent", "a", "friend", "-"], {"1": "56", "3": "36"}], [["Then", "we", "hide", "our", "brave", "face"], {"2": "70", "4": "23", "5": "70"}], [["Deep", "in", "our", "hand", "-"], {"0": "70", "3": "36"}], [["Not", "to", "cry", "-", "Tim", "and", "I", "-"], {"2": "36", "4": "56"}], [["We", "are", "far", "too", "grand", "-"], {"4": "70"}], [["Nor", "to", "dream", "-", "he", "and", "me", "-"], {"2": "56"}], [["Do", "we", "condescend", "-"], {"2": "56"}], [["We", "just", "shut", "our", "brown", "eye"], {"2": "70", "4": "56", "5": "70"}], [["To", "see", "to", "the", "end", "-"], {"4": "19"}], [["Tim", "-", "see", "Cottages", "-"], {"0": "56", "3": "70"}], [["But,", "Oh,", "so", "high!"], {"3": "70"}], [["Then", "-", "we", "shake", "-", "Tim", "and", "I", "-"], {"3": "56", "5": "56"}], [["And", "lest", "I", "-", "cry", "-"], {"4": "36"}], [["Tim", "-", "reads", "a", "little", "Hymn", "-"], {"0": "56", "2": "70", "5": "61"}], [["And", "we", "both", "pray,"], {"3": "12"}], [["Please,", "Sir,", "I", "and", "Tim", "-"], {"1": "70", "4": "56"}], [["Always", "lost", "the", "way!"], {"1": "70"}], [["We", "must", "die", "-", "by", "and", "by", "-"], {"2": "5"}], [["Clergymen", "say", "-"], {"0": "56"}], [["Tim", "-", "shall", "-", "if", "I", "-", "do", "-"], {"0": "56"}], [["I", "-", "too", "-", "if", "he", "-"], {}], [["How", "shall", "we", "arrange", "it", "-"], {"3": "70"}], [["Tim", "-", "was", "-", "so", "-", "shy?"], {"0": "56", "6": "56"}], [["Take", "us", "simultaneous", "-", "Lord", "-"], {"2": "96", "4": "70"}], [["I", "-", "\"Tim\"", "-", "and", "-", "me!"], {"2": "56"}], [[""], {}]], "full_text": "<xhtml:p class=\"text_p\"><xhtml:span class=\"text_edgespan\">&nbsp;</xhtml:span></xhtml:p><xhtml:p class=\"text_p\"><xhtml:span class=\"text_edgespan\">&nbsp;&nbsp;&nbsp;&nbsp;</xhtml:span><xhtml:span class=\"text_word\">We&nbsp;</xhtml:span><xhtml:span class=\"text_coloredword\" style=\"color:#c094ff\">dont&nbsp;</xhtml:span><xhtml:span class=\"text_coloredword\" style=\"color:#98acdc\">cry&nbsp;</xhtml:span><xhtml:span class=\"text_word\">-&nbsp;</xhtml:span><xhtml:span class=\"text_coloredword\" style=\"color:#f45c7c\">Tim&nbsp;</xhtml:span><xhtml:span class=\"text_word\">and&nbsp;</xhtml:span><xhtml:span class=\"text_word\">I&nbsp;</xhtml:span><xhtml:span class=\"text_word\">-&nbsp;</xhtml:span></xhtml:p><xhtml:p class=\"text_p\"><xhtml:span class=\"text_edgespan\">&nbsp;&nbsp;&nbsp;&nbsp;</xhtml:span><xhtml:span class=\"text_word\">We&nbsp;</xhtml:span><xhtml:span class=\"text_word\">are&nbsp;</xhtml:span><xhtml:span class=\"text_word\">far&nbsp;</xhtml:span><xhtml:span class=\"text_word\">too&nbsp;</xhtml:span><xhtml:span class=\"text_coloredword\" style=\"color:#c094ff\">grand&nbsp;</xhtml:span><xhtml:span class=\"text_word\">-&nbsp;</xhtml:span></xhtml:p><xhtml:p class=\"text_p\"><xhtml:span class=\"text_edgespan\">&nbsp;&nbsp;&nbsp;&nbsp;</xhtml:span><xhtml:span class=\"text_word\">But&nbsp;</xhtml:span><xhtml:span class=\"text_word\">we&nbsp;</xhtml:span><xhtml:span class=\"text_coloredword\" style=\"color:#f45c7c\">bolt&nbsp;</xhtml:span><xhtml:span class=\"text_word\">the&nbsp;</xhtml:span><xhtml:span class=\"text_coloredword\" style=\"color:#04c4ff\">door&nbsp;</xhtml:span><xhtml:span class=\"text_coloredword\" style=\"color:#f45c7c\">tight&nbsp;</xhtml:span></xhtml:p><xhtml:p class=\"text_p\"><xhtml:span class=\"text_edgespan\">&nbsp;&nbsp;&nbsp;&nbsp;</xhtml:span><xhtml:span class=\"text_word\">To&nbsp;</xhtml:span><xhtml:span class=\"text_coloredword\" style=\"color:#f45c7c\">prevent&nbsp;</xhtml:span><xhtml:span class=\"text_word\">a&nbsp;</xhtml:span><xhtml:span class=\"text_coloredword\" style=\"color:#98acdc\">friend&nbsp;</xhtml:span><xhtml:span class=\"text_word\">-&nbsp;</xhtml:span></xhtml:p><xhtml:p class=\"text_p\"><xhtml:span class=\"text_edgespan\">&nbsp;&nbsp;&nbsp;&nbsp;</xhtml:span><xhtml:span class=\"text_word\">Then&nbsp;</xhtml:span><xhtml:span class=\"text_word\">we&nbsp;</xhtml:span><xhtml:span class=\"text_coloredword\" style=\"color:#c094ff\">hide&nbsp;</xhtml:span><xhtml:span class=\"text_word\">our&nbsp;</xhtml:span><xhtml:span class=\"text_coloredword\" style=\"color:#84643c\">brave&nbsp;</xhtml:span><xhtml:span class=\"text_coloredword\" style=\"color:#c094ff\">face&nbsp;</xhtml:span></xhtml:p><xhtml:p class=\"text_p\"><xhtml:span class=\"text_edgespan\">&nbsp;&nbsp;&nbsp;&nbsp;</xhtml:span><xhtml:span class=\"text_coloredword\" style=\"color:#c094ff\">Deep&nbsp;</xhtml:span><xhtml:span class=\"text_word\">in&nbsp;</xhtml:span><xhtml:span class=\"text_word\">our&nbsp;</xhtml:span><xhtml:span class=\"text_coloredword\" style=\"color:#98acdc\">hand&nbsp;</xhtml:span><xhtml:span class=\"text_word\">-&nbsp;</xhtml:span></xhtml:p><xhtml:p class=\"text_p\"><xhtml:span class=\"text_edgespan\">&nbsp;&nbsp;&nbsp;&nbsp;</xhtml:span><xhtml:span class=\"text_word\">Not&nbsp;</xhtml:span><xhtml:span class=\"text_word\">to&nbsp;</xhtml:span><xhtml:span class=\"text_coloredword\" style=\"color:#98acdc\">cry&nbsp;</xhtml:span><xhtml:span class=\"text_word\">-&nbsp;</xhtml:span><xhtml:span class=\"text_coloredword\" style=\"color:#f45c7c\">Tim&nbsp;</xhtml:span><xhtml:span class=\"text_word\">and&nbsp;</xhtml:span><xhtml:span class=\"text_word\">I&nbsp;</xhtml:span><xhtml:span class=\"text_word\">-&nbsp;</xhtml:span></xhtml:p><xhtml:p class=\"text_p\"><xhtml:span class=\"text_edgespan\">&nbsp;&nbsp;&nbsp;&nbsp;</xhtml:span><xhtml:span class=\"text_word\">We&nbsp;</xhtml:span><xhtml:span class=\"text_word\">are&nbsp;</xhtml:span><xhtml:span class=\"text_word\">far&nbsp;</xhtml:span><xhtml:span class=\"text_word\">too&nbsp;</xhtml:span><xhtml:span class=\"text_coloredword\" style=\"color:#c094ff\">grand&nbsp;</xhtml:span><xhtml:span class=\"text_word\">-&nbsp;</xhtml:span></xhtml:p><xhtml:p class=\"text_p\"><xhtml:span class=\"text_edgespan\">&nbsp;&nbsp;&nbsp;&nbsp;</xhtml:span><xhtml:span class=\"text_word\">Nor&nbsp;</xhtml:span><xhtml:span class=\"text_word\">to&nbsp;</xhtml:span><xhtml:span class=\"text_coloredword\" style=\"color:#f45c7c\">dream&nbsp;</xhtml:span><xhtml:span class=\"text_word\">-&nbsp;</xhtml:span><xhtml:span class=\"text_word\">he&nbsp;</xhtml:span><xhtml:span class=\"text_word\">and&nbsp;</xhtml:span><xhtml:span class=\"text_word\">me&nbsp;</xhtml:span><xhtml:span class=\"text_word\">-&nbsp;</xhtml:span></xhtml:p><xhtml:p class=\"text_p\"><xhtml:span class=\"text_edgespan\">&nbsp;&nbsp;&nbsp;&nbsp;</xhtml:span><xhtml:span class=\"text_word\">Do&nbsp;</xhtml:span><xhtml:span class=\"text_word\">we&nbsp;</xhtml:span><xhtml:span class=\"text_coloredword\" style=\"color:#f45c7c\">condescend&nbsp;</xhtml:span><xhtml:span class=\"text_word\">-&nbsp;</xhtml:span></xhtml:p><xhtml:p class=\"text_p\"><xhtml:span class=\"text_edgespan\">&nbsp;&nbsp;&nbsp;&nbsp;</xhtml:span><xhtml:span class=\"text_word\">We&nbsp;</xhtml:span><xhtml:span class=\"text_word\">just&nbsp;</xhtml:span><xhtml:span class=\"text_coloredword\" style=\"color:#c094ff\">shut&nbsp;</xhtml:span><xhtml:span class=\"text_word\">our&nbsp;</xhtml:span><xhtml:span class=\"text_coloredword\" style=\"color:#f45c7c\">brown&nbsp;</xhtml:span><xhtml:span class=\"text_coloredword\" style=\"color:#c094ff\">eye&nbsp;</xhtml:span></xhtml:p><xhtml:p class=\"text_p\"><xhtml:span class=\"text_edgespan\">&nbsp;&nbsp;&nbsp;&nbsp;</xhtml:span><xhtml:span class=\"text_word\">To&nbsp;</xhtml:span><xhtml:span class=\"text_word\">see&nbsp;</xhtml:span><xhtml:span class=\"text_word\">to&nbsp;</xhtml:span><xhtml:span class=\"text_word\">the&nbsp;</xhtml:span><xhtml:span class=\"text_coloredword\" style=\"color:#e86450\">end&nbsp;</xhtml:span><xhtml:span class=\"text_word\">-&nbsp;</xhtml:span></xhtml:p><xhtml:p class=\"text_p\"><xhtml:span class=\"text_edgespan\">&nbsp;&nbsp;&nbsp;&nbsp;</xhtml:span><xhtml:span class=\"text_coloredword\" style=\"color:#f45c7c\">Tim&nbsp;</xhtml:span><xhtml:span class=\"text_word\">-&nbsp;</xhtml:span><xhtml:span class=\"text_word\">see&nbsp;</xhtml:span><xhtml:span class=\"text_coloredword\" style=\"color:#c094ff\">Cottages&nbsp;</xhtml:span><xhtml:span class=\"text_word\">-&nbsp;</xhtml:span></xhtml:p><xhtml:p class=\"text_p\"><xhtml:span class=\"text_edgespan\">&nbsp;&nbsp;&nbsp;&nbsp;</xhtml:span><xhtml:span class=\"text_word\">But,&nbsp;</xhtml:span><xhtml:span class=\"text_word\">Oh,&nbsp;</xhtml:span><xhtml:span class=\"text_word\">so&nbsp;</xhtml:span><xhtml:span class=\"text_coloredword\" style=\"color:#c094ff\">high!&nbsp;</xhtml:span></xhtml:p><xhtml:p class=\"text_p\"><xhtml:span class=\"text_edgespan\">&nbsp;&nbsp;&nbsp;&nbsp;</xhtml:span><xhtml:span class=\"text_word\">Then&nbsp;</xhtml:span><xhtml:span class=\"text_word\">-&nbsp;</xhtml:span><xhtml:span class=\"text_word\">we&nbsp;</xhtml:span><xhtml:span class=\"text_coloredword\" style=\"color:#f45c7c\">shake&nbsp;</xhtml:span><xhtml:span class=\"text_word\">-&nbsp;</xhtml:span><xhtml:span class=\"text_coloredword\" style=\"color:#f45c7c\">Tim&nbsp;</xhtml:span><xhtml:span class=\"text_word\">and&nbsp;</xhtml:span><xhtml:span class=\"text_word\">I&nbsp;</xhtml:span><xhtml:span class=\"text_word\">-&nbsp;</xhtml:span></xhtml:p><xhtml:p class=\"text_p\"><xhtml:span class=\"text_edgespan\">&nbsp;&nbsp;&nbsp;&nbsp;</xhtml:span><xhtml:span class=\"text_word\">And&nbsp;</xhtml:span><xhtml:span class=\"text_word\">lest&nbsp;</xhtml:span><xhtml:span class=\"text_word\">I&nbsp;</xhtml:span><xhtml:span class=\"text_word\">-&nbsp;</xhtml:span><xhtml:span class=\"text_coloredword\" style=\"color:#98acdc\">cry&nbsp;</xhtml:span><xhtml:span class=\"text_word\">-&nbsp;</xhtml:span></xhtml:p><xhtml:p class=\"text_p\"><xhtml:span class=\"text_edgespan\">&nbsp;&nbsp;&nbsp;&nbsp;</xhtml:span><xhtml:span class=\"text_coloredword\" style=\"color:#f45c7c\">Tim&nbsp;</xhtml:span><xhtml:span class=\"text_word\">-&nbsp;</xhtml:span><xhtml:span class=\"text_coloredword\" style=\"color:#c094ff\">reads&nbsp;</xhtml:span><xhtml:span class=\"text_word\">a&nbsp;</xhtml:span><xhtml:span class=\"text_word\">little&nbsp;</xhtml:span><xhtml:span class=\"text_coloredword\" style=\"color:#04c4ff\">Hymn&nbsp;</xhtml:span><xhtml:span class=\"text_word\">-&nbsp;</xhtml:span></xhtml:p><xhtml:p class=\"text_p\"><xhtml:span class=\"text_edgespan\">&nbsp;&nbsp;&nbsp;&nbsp;</xhtml:span><xhtml:span class=\"text_word\">And&nbsp;</xhtml:span><xhtml:span class=\"text_word\">we&nbsp;</xhtml:span><xhtml:span class=\"text_word\">both&nbsp;</xhtml:span><xhtml:span class=\"text_coloredword\" style=\"color:#f0ccff\">pray,&nbsp;</xhtml:span></xhtml:p><xhtml:p class=\"text_p\"><xhtml:span class=\"text_edgespan\">&nbsp;&nbsp;&nbsp;&nbsp;</xhtml:span><xhtml:span class=\"text_word\">Please,&nbsp;</xhtml:span><xhtml:span class=\"text_coloredword\" style=\"color:#c094ff\">Sir,&nbsp;</xhtml:span><xhtml:span class=\"text_word\">I&nbsp;</xhtml:span><xhtml:span class=\"text_word\">and&nbsp;</xhtml:span><xhtml:span class=\"text_coloredword\" style=\"color:#f45c7c\">Tim&nbsp;</xhtml:span><xhtml:span class=\"text_word\">-&nbsp;</xhtml:span></xhtml:p><xhtml:p class=\"text_p\"><xhtml:span class=\"text_edgespan\">&nbsp;&nbsp;&nbsp;&nbsp;</xhtml:span><xhtml:span class=\"text_word\">Always&nbsp;</xhtml:span><xhtml:span class=\"text_coloredword\" style=\"color:#c094ff\">lost&nbsp;</xhtml:span><xhtml:span class=\"text_word\">the&nbsp;</xhtml:span><xhtml:span class=\"text_word\">way!&nbsp;</xhtml:span></xhtml:p><xhtml:p class=\"text_p\"><xhtml:span class=\"text_edgespan\">&nbsp;&nbsp;&nbsp;&nbsp;</xhtml:span><xhtml:span class=\"text_word\">We&nbsp;</xhtml:span><xhtml:span class=\"text_word\">must&nbsp;</xhtml:span><xhtml:span class=\"text_coloredword\" style=\"color:#ecb894\">die&nbsp;</xhtml:span><xhtml:span class=\"text_word\">-&nbsp;</xhtml:span><xhtml:span class=\"text_word\">by&nbsp;</xhtml:span><xhtml:span class=\"text_word\">and&nbsp;</xhtml:span><xhtml:span class=\"text_word\">by&nbsp;</xhtml:span><xhtml:span class=\"text_word\">-&nbsp;</xhtml:span></xhtml:p><xhtml:p class=\"text_p\"><xhtml:span class=\"text_edgespan\">&nbsp;&nbsp;&nbsp;&nbsp;</xhtml:span><xhtml:span class=\"text_coloredword\" style=\"color:#f45c7c\">Clergymen&nbsp;</xhtml:span><xhtml:span class=\"text_word\">say&nbsp;</xhtml:span><xhtml:span class=\"text_word\">-&nbsp;</xhtml:span></xhtml:p><xhtml:p class=\"text_p\"><xhtml:span class=\"text_edgespan\">&nbsp;&nbsp;&nbsp;&nbsp;</xhtml:span><xhtml:span class=\"text_coloredword\" style=\"color:#f45c7c\">Tim&nbsp;</xhtml:span><xhtml:span class=\"text_word\">-&nbsp;</xhtml:span><xhtml:span class=\"text_word\">shall&nbsp;</xhtml:span><xhtml:span class=\"text_word\">-&nbsp;</xhtml:span><xhtml:span class=\"text_word\">if&nbsp;</xhtml:span><xhtml:span class=\"text_word\">I&nbsp;</xhtml:span><xhtml:span class=\"text_word\">-&nbsp;</xhtml:span><xhtml:span class=\"text_word\">do&nbsp;</xhtml:span><xhtml:span class=\"text_word\">-&nbsp;</xhtml:span></xhtml:p><xhtml:p class=\"text_p\"><xhtml:span class=\"text_edgespan\">&nbsp;&nbsp;&nbsp;&nbsp;</xhtml:span><xhtml:span class=\"text_word\">I&nbsp;</xhtml:span><xhtml:span class=\"text_word\">-&nbsp;</xhtml:span><xhtml:span class=\"text_word\">too&nbsp;</xhtml:span><xhtml:span class=\"text_word\">-&nbsp;</xhtml:span><xhtml:span class=\"text_word\">if&nbsp;</xhtml:span><xhtml:span class=\"text_word\">he&nbsp;</xhtml:span><xhtml:span class=\"text_word\">-&nbsp;</xhtml:span></xhtml:p><xhtml:p class=\"text_p\"><xhtml:span class=\"text_edgespan\">&nbsp;&nbsp;&nbsp;&nbsp;</xhtml:span><xhtml:span class=\"text_word\">How&nbsp;</xhtml:span><xhtml:span class=\"text_word\">shall&nbsp;</xhtml:span><xhtml:span class=\"text_word\">we&nbsp;</xhtml:span><xhtml:span class=\"text_coloredword\" style=\"color:#c094ff\">arrange&nbsp;</xhtml:span><xhtml:span class=\"text_word\">it&nbsp;</xhtml:span><xhtml:span class=\"text_word\">-&nbsp;</xhtml:span></xhtml:p><xhtml:p class=\"text_p\"><xhtml:span class=\"text_edgespan\">&nbsp;&nbsp;&nbsp;&nbsp;</xhtml:span><xhtml:span class=\"text_coloredword\" style=\"color:#f45c7c\">Tim&nbsp;</xhtml:span><xhtml:span class=\"text_word\">-&nbsp;</xhtml:span><xhtml:span class=\"text_word\">was&nbsp;</xhtml:span><xhtml:span class=\"text_word\">-&nbsp;</xhtml:span><xhtml:span class=\"text_word\">so&nbsp;</xhtml:span><xhtml:span class=\"text_word\">-&nbsp;</xhtml:span><xhtml:span class=\"text_coloredword\" style=\"color:#f45c7c\">shy?&nbsp;</xhtml:span></xhtml:p><xhtml:p class=\"text_p\"><xhtml:span class=\"text_edgespan\">&nbsp;&nbsp;&nbsp;&nbsp;</xhtml:span><xhtml:span class=\"text_word\">Take&nbsp;</xhtml:span><xhtml:span class=\"text_word\">us&nbsp;</xhtml:span><xhtml:span class=\"text_coloredword\" style=\"color:#70e0ff\">simultaneous&nbsp;</xhtml:span><xhtml:span class=\"text_word\">-&nbsp;</xhtml:span><xhtml:span class=\"text_coloredword\" style=\"color:#c094ff\">Lord&nbsp;</xhtml:span><xhtml:span class=\"text_word\">-&nbsp;</xhtml:span></xhtml:p><xhtml:p class=\"text_p\"><xhtml:span class=\"text_edgespan\">&nbsp;&nbsp;&nbsp;&nbsp;</xhtml:span><xhtml:span class=\"text_word\">I&nbsp;</xhtml:span><xhtml:span class=\"text_word\">-&nbsp;</xhtml:span><xhtml:span class=\"text_coloredword\" style=\"color:#f45c7c\">\"Tim\"&nbsp;</xhtml:span><xhtml:span class=\"text_word\">-&nbsp;</xhtml:span><xhtml:span class=\"text_word\">and&nbsp;</xhtml:span><xhtml:span class=\"text_word\">-&nbsp;</xhtml:span><xhtml:span class=\"text_word\">me!&nbsp;</xhtml:span></xhtml:p><xhtml:p class=\"text_p\"><xhtml:span class=\"text_edgespan\">&nbsp;&nbsp;&nbsp;&nbsp;</xhtml:span><xhtml:span class=\"text_word\">&nbsp;</xhtml:span></xhtml:p>", "line_count": 29}}