{"document": {"filename": "1203_2446_0", "title": "2446_0", "lines_and_colors": [[["To", "lose", "thee", "-", "sweeter", "than", "to", "gain"], {"1": "48", "2": "4", "4": "4", "7": "46"}], [["All", "other", "hearts", "I", "knew."], {"2": "40", "4": "84"}], [["'Tis", "true", "the", "drought", "is", "destitute,"], {"0": "40", "1": "84", "3": "84", "5": "84"}], [["But", "then,", "I", "had", "the", "dew!"], {"5": "4"}], [["The", "Caspian", "has", "it's", "realms", "of", "sand,"], {"1": "84", "3": "84", "4": "90", "6": "48"}], [["It's", "other", "realm", "of", "sea."], {"0": "84", "2": "46", "4": "90"}], [["Without", "the", "sterile", "perquisite,"], {"2": "48", "3": "90"}], [["No", "Caspian", "could", "be."], {"1": "84"}], [[""], {}]], "full_text": "<xhtml:p class=\"text_p\"><xhtml:span class=\"text_edgespan\">&nbsp;</xhtml:span></xhtml:p><xhtml:p class=\"text_p\"><xhtml:span class=\"text_edgespan\">&nbsp;&nbsp;&nbsp;&nbsp;</xhtml:span><xhtml:span class=\"text_word\">To&nbsp;</xhtml:span><xhtml:span class=\"text_coloredword\" style=\"color:#d4ccff\">lose&nbsp;</xhtml:span><xhtml:span class=\"text_coloredword\" style=\"color:#ffa06e\">thee&nbsp;</xhtml:span><xhtml:span class=\"text_word\">-&nbsp;</xhtml:span><xhtml:span class=\"text_coloredword\" style=\"color:#ffa06e\">sweeter&nbsp;</xhtml:span><xhtml:span class=\"text_word\">than&nbsp;</xhtml:span><xhtml:span class=\"text_word\">to&nbsp;</xhtml:span><xhtml:span class=\"text_coloredword\" style=\"color:#64ff90\">gain&nbsp;</xhtml:span></xhtml:p><xhtml:p class=\"text_p\"><xhtml:span class=\"text_edgespan\">&nbsp;&nbsp;&nbsp;&nbsp;</xhtml:span><xhtml:span class=\"text_word\">All&nbsp;</xhtml:span><xhtml:span class=\"text_word\">other&nbsp;</xhtml:span><xhtml:span class=\"text_coloredword\" style=\"color:#64b8ff\">hearts&nbsp;</xhtml:span><xhtml:span class=\"text_word\">I&nbsp;</xhtml:span><xhtml:span class=\"text_coloredword\" style=\"color:#447cff\">knew.&nbsp;</xhtml:span></xhtml:p><xhtml:p class=\"text_p\"><xhtml:span class=\"text_edgespan\">&nbsp;&nbsp;&nbsp;&nbsp;</xhtml:span><xhtml:span class=\"text_coloredword\" style=\"color:#64b8ff\">'Tis&nbsp;</xhtml:span><xhtml:span class=\"text_coloredword\" style=\"color:#447cff\">true&nbsp;</xhtml:span><xhtml:span class=\"text_word\">the&nbsp;</xhtml:span><xhtml:span class=\"text_coloredword\" style=\"color:#447cff\">drought&nbsp;</xhtml:span><xhtml:span class=\"text_word\">is&nbsp;</xhtml:span><xhtml:span class=\"text_coloredword\" style=\"color:#447cff\">destitute,&nbsp;</xhtml:span></xhtml:p><xhtml:p class=\"text_p\"><xhtml:span class=\"text_edgespan\">&nbsp;&nbsp;&nbsp;&nbsp;</xhtml:span><xhtml:span class=\"text_word\">But&nbsp;</xhtml:span><xhtml:span class=\"text_word\">then,&nbsp;</xhtml:span><xhtml:span class=\"text_word\">I&nbsp;</xhtml:span><xhtml:span class=\"text_word\">had&nbsp;</xhtml:span><xhtml:span class=\"text_word\">the&nbsp;</xhtml:span><xhtml:span class=\"text_coloredword\" style=\"color:#ffa06e\">dew!&nbsp;</xhtml:span></xhtml:p><xhtml:p class=\"text_p\"><xhtml:span class=\"text_edgespan\">&nbsp;&nbsp;&nbsp;&nbsp;</xhtml:span><xhtml:span class=\"text_word\">The&nbsp;</xhtml:span><xhtml:span class=\"text_coloredword\" style=\"color:#447cff\">Caspian&nbsp;</xhtml:span><xhtml:span class=\"text_word\">has&nbsp;</xhtml:span><xhtml:span class=\"text_coloredword\" style=\"color:#447cff\">it's&nbsp;</xhtml:span><xhtml:span class=\"text_coloredword\" style=\"color:#98e8ff\">realms&nbsp;</xhtml:span><xhtml:span class=\"text_word\">of&nbsp;</xhtml:span><xhtml:span class=\"text_coloredword\" style=\"color:#d4ccff\">sand,&nbsp;</xhtml:span></xhtml:p><xhtml:p class=\"text_p\"><xhtml:span class=\"text_edgespan\">&nbsp;&nbsp;&nbsp;&nbsp;</xhtml:span><xhtml:span class=\"text_coloredword\" style=\"color:#447cff\">It's&nbsp;</xhtml:span><xhtml:span class=\"text_word\">other&nbsp;</xhtml:span><xhtml:span class=\"text_coloredword\" style=\"color:#64ff90\">realm&nbsp;</xhtml:span><xhtml:span class=\"text_word\">of&nbsp;</xhtml:span><xhtml:span class=\"text_coloredword\" style=\"color:#98e8ff\">sea.&nbsp;</xhtml:span></xhtml:p><xhtml:p class=\"text_p\"><xhtml:span class=\"text_edgespan\">&nbsp;&nbsp;&nbsp;&nbsp;</xhtml:span><xhtml:span class=\"text_word\">Without&nbsp;</xhtml:span><xhtml:span class=\"text_word\">the&nbsp;</xhtml:span><xhtml:span class=\"text_coloredword\" style=\"color:#d4ccff\">sterile&nbsp;</xhtml:span><xhtml:span class=\"text_coloredword\" style=\"color:#98e8ff\">perquisite,&nbsp;</xhtml:span></xhtml:p><xhtml:p class=\"text_p\"><xhtml:span class=\"text_edgespan\">&nbsp;&nbsp;&nbsp;&nbsp;</xhtml:span><xhtml:span class=\"text_word\">No&nbsp;</xhtml:span><xhtml:span class=\"text_coloredword\" style=\"color:#447cff\">Caspian&nbsp;</xhtml:span><xhtml:span class=\"text_word\">could&nbsp;</xhtml:span><xhtml:span class=\"text_word\">be.&nbsp;</xhtml:span></xhtml:p><xhtml:p class=\"text_p\"><xhtml:span class=\"text_edgespan\">&nbsp;&nbsp;&nbsp;&nbsp;</xhtml:span><xhtml:span class=\"text_word\">&nbsp;</xhtml:span></xhtml:p>", "line_count": 9}}