{"document": {"filename": "1210_96_0", "title": "96_0", "lines_and_colors": [[["Some", "things", "that", "fly", "there", "be", "-"], {"1": "19", "3": "91"}], [["Birds", "-", "Hours", "-", "the", "Bumblebee", "-"], {"0": "13", "2": "64", "5": "19"}], [["Of", "these", "no", "Elegy."], {"3": "43"}], [["Some", "things", "that", "stay", "there", "be", "-"], {"1": "19", "3": "64"}], [["Grief", "-", "Hills", "-", "Eternity", "-"], {"0": "0", "2": "91", "4": "19"}], [["Nor", "this", "behooveth", "me."], {"2": "74"}], [["There", "are", "that", "resting,", "rise."], {"3": "74", "4": "64"}], [["Can", "I", "expound", "the", "skies?"], {"2": "19", "4": "91"}], [["How", "still", "the", "Riddle", "lies!"], {"3": "91", "4": "78"}], [[""], {}]], "full_text": "<xhtml:p class=\"text_p\"><xhtml:span class=\"text_edgespan\">&nbsp;</xhtml:span></xhtml:p><xhtml:p class=\"text_p\"><xhtml:span class=\"text_edgespan\">&nbsp;&nbsp;&nbsp;&nbsp;</xhtml:span><xhtml:span class=\"text_word\">Some&nbsp;</xhtml:span><xhtml:span class=\"text_coloredword\" style=\"color:#e86450\">things&nbsp;</xhtml:span><xhtml:span class=\"text_word\">that&nbsp;</xhtml:span><xhtml:span class=\"text_coloredword\" style=\"color:#c4c8ff\">fly&nbsp;</xhtml:span><xhtml:span class=\"text_word\">there&nbsp;</xhtml:span><xhtml:span class=\"text_word\">be&nbsp;</xhtml:span><xhtml:span class=\"text_word\">-&nbsp;</xhtml:span></xhtml:p><xhtml:p class=\"text_p\"><xhtml:span class=\"text_edgespan\">&nbsp;&nbsp;&nbsp;&nbsp;</xhtml:span><xhtml:span class=\"text_coloredword\" style=\"color:#4064ff\">Birds&nbsp;</xhtml:span><xhtml:span class=\"text_word\">-&nbsp;</xhtml:span><xhtml:span class=\"text_coloredword\" style=\"color:#4cacc0\">Hours&nbsp;</xhtml:span><xhtml:span class=\"text_word\">-&nbsp;</xhtml:span><xhtml:span class=\"text_word\">the&nbsp;</xhtml:span><xhtml:span class=\"text_coloredword\" style=\"color:#e86450\">Bumblebee&nbsp;</xhtml:span><xhtml:span class=\"text_word\">-&nbsp;</xhtml:span></xhtml:p><xhtml:p class=\"text_p\"><xhtml:span class=\"text_edgespan\">&nbsp;&nbsp;&nbsp;&nbsp;</xhtml:span><xhtml:span class=\"text_word\">Of&nbsp;</xhtml:span><xhtml:span class=\"text_word\">these&nbsp;</xhtml:span><xhtml:span class=\"text_word\">no&nbsp;</xhtml:span><xhtml:span class=\"text_coloredword\" style=\"color:#2828ff\">Elegy.&nbsp;</xhtml:span></xhtml:p><xhtml:p class=\"text_p\"><xhtml:span class=\"text_edgespan\">&nbsp;&nbsp;&nbsp;&nbsp;</xhtml:span><xhtml:span class=\"text_word\">Some&nbsp;</xhtml:span><xhtml:span class=\"text_coloredword\" style=\"color:#e86450\">things&nbsp;</xhtml:span><xhtml:span class=\"text_word\">that&nbsp;</xhtml:span><xhtml:span class=\"text_coloredword\" style=\"color:#4cacc0\">stay&nbsp;</xhtml:span><xhtml:span class=\"text_word\">there&nbsp;</xhtml:span><xhtml:span class=\"text_word\">be&nbsp;</xhtml:span><xhtml:span class=\"text_word\">-&nbsp;</xhtml:span></xhtml:p><xhtml:p class=\"text_p\"><xhtml:span class=\"text_edgespan\">&nbsp;&nbsp;&nbsp;&nbsp;</xhtml:span><xhtml:span class=\"text_coloredword\" style=\"color:#ff645c\">Grief&nbsp;</xhtml:span><xhtml:span class=\"text_word\">-&nbsp;</xhtml:span><xhtml:span class=\"text_coloredword\" style=\"color:#c4c8ff\">Hills&nbsp;</xhtml:span><xhtml:span class=\"text_word\">-&nbsp;</xhtml:span><xhtml:span class=\"text_coloredword\" style=\"color:#e86450\">Eternity&nbsp;</xhtml:span><xhtml:span class=\"text_word\">-&nbsp;</xhtml:span></xhtml:p><xhtml:p class=\"text_p\"><xhtml:span class=\"text_edgespan\">&nbsp;&nbsp;&nbsp;&nbsp;</xhtml:span><xhtml:span class=\"text_word\">Nor&nbsp;</xhtml:span><xhtml:span class=\"text_word\">this&nbsp;</xhtml:span><xhtml:span class=\"text_coloredword\" style=\"color:#107cff\">behooveth&nbsp;</xhtml:span><xhtml:span class=\"text_word\">me.&nbsp;</xhtml:span></xhtml:p><xhtml:p class=\"text_p\"><xhtml:span class=\"text_edgespan\">&nbsp;&nbsp;&nbsp;&nbsp;</xhtml:span><xhtml:span class=\"text_word\">There&nbsp;</xhtml:span><xhtml:span class=\"text_word\">are&nbsp;</xhtml:span><xhtml:span class=\"text_word\">that&nbsp;</xhtml:span><xhtml:span class=\"text_coloredword\" style=\"color:#107cff\">resting,&nbsp;</xhtml:span><xhtml:span class=\"text_coloredword\" style=\"color:#4cacc0\">rise.&nbsp;</xhtml:span></xhtml:p><xhtml:p class=\"text_p\"><xhtml:span class=\"text_edgespan\">&nbsp;&nbsp;&nbsp;&nbsp;</xhtml:span><xhtml:span class=\"text_word\">Can&nbsp;</xhtml:span><xhtml:span class=\"text_word\">I&nbsp;</xhtml:span><xhtml:span class=\"text_coloredword\" style=\"color:#e86450\">expound&nbsp;</xhtml:span><xhtml:span class=\"text_word\">the&nbsp;</xhtml:span><xhtml:span class=\"text_coloredword\" style=\"color:#c4c8ff\">skies?&nbsp;</xhtml:span></xhtml:p><xhtml:p class=\"text_p\"><xhtml:span class=\"text_edgespan\">&nbsp;&nbsp;&nbsp;&nbsp;</xhtml:span><xhtml:span class=\"text_word\">How&nbsp;</xhtml:span><xhtml:span class=\"text_word\">still&nbsp;</xhtml:span><xhtml:span class=\"text_word\">the&nbsp;</xhtml:span><xhtml:span class=\"text_coloredword\" style=\"color:#c4c8ff\">Riddle&nbsp;</xhtml:span><xhtml:span class=\"text_coloredword\" style=\"color:#b844ff\">lies!&nbsp;</xhtml:span></xhtml:p><xhtml:p class=\"text_p\"><xhtml:span class=\"text_edgespan\">&nbsp;&nbsp;&nbsp;&nbsp;</xhtml:span><xhtml:span class=\"text_word\">&nbsp;</xhtml:span></xhtml:p>", "line_count": 10}}