{"document": {"filename": "1512_218_0", "title": "218_0", "lines_and_colors": [[["I", "never", "hear", "the", "word", "'Escape'"], {"2": "17", "4": "64", "5": "64"}], [["Without", "a", "quicker", "blood!"], {"2": "29", "3": "88"}], [["A", "sudden", "expectation!"], {"1": "67", "2": "88"}], [["A", "flying", "attitude!"], {"1": "64", "2": "17"}], [["I", "never", "hear", "of", "prisons", "broad"], {"2": "17", "4": "29", "5": "38"}], [["By", "soldiers", "battered", "down", "-"], {"1": "2", "2": "17"}], [["But", "I", "tug,", "childish,", "at", "my", "bars", "-"], {"2": "17", "3": "64", "6": "81"}], [["Only", "to", "fail", "again!"], {"2": "17"}], [[""], {}]], "full_text": "<xhtml:p class=\"text_p\"><xhtml:span class=\"text_edgespan\">&nbsp;</xhtml:span></xhtml:p><xhtml:p class=\"text_p\"><xhtml:span class=\"text_edgespan\">&nbsp;&nbsp;&nbsp;&nbsp;</xhtml:span><xhtml:span class=\"text_word\">I&nbsp;</xhtml:span><xhtml:span class=\"text_word\">never&nbsp;</xhtml:span><xhtml:span class=\"text_coloredword\" style=\"color:#94ffb6\">hear&nbsp;</xhtml:span><xhtml:span class=\"text_word\">the&nbsp;</xhtml:span><xhtml:span class=\"text_coloredword\" style=\"color:#4cacc0\">word&nbsp;</xhtml:span><xhtml:span class=\"text_coloredword\" style=\"color:#4cacc0\">'Escape'&nbsp;</xhtml:span></xhtml:p><xhtml:p class=\"text_p\"><xhtml:span class=\"text_edgespan\">&nbsp;&nbsp;&nbsp;&nbsp;</xhtml:span><xhtml:span class=\"text_word\">Without&nbsp;</xhtml:span><xhtml:span class=\"text_word\">a&nbsp;</xhtml:span><xhtml:span class=\"text_coloredword\" style=\"color:#ff08b4\">quicker&nbsp;</xhtml:span><xhtml:span class=\"text_coloredword\" style=\"color:#889098\">blood!&nbsp;</xhtml:span></xhtml:p><xhtml:p class=\"text_p\"><xhtml:span class=\"text_edgespan\">&nbsp;&nbsp;&nbsp;&nbsp;</xhtml:span><xhtml:span class=\"text_word\">A&nbsp;</xhtml:span><xhtml:span class=\"text_coloredword\" style=\"color:#50d0ff\">sudden&nbsp;</xhtml:span><xhtml:span class=\"text_coloredword\" style=\"color:#889098\">expectation!&nbsp;</xhtml:span></xhtml:p><xhtml:p class=\"text_p\"><xhtml:span class=\"text_edgespan\">&nbsp;&nbsp;&nbsp;&nbsp;</xhtml:span><xhtml:span class=\"text_word\">A&nbsp;</xhtml:span><xhtml:span class=\"text_coloredword\" style=\"color:#4cacc0\">flying&nbsp;</xhtml:span><xhtml:span class=\"text_coloredword\" style=\"color:#94ffb6\">attitude!&nbsp;</xhtml:span></xhtml:p><xhtml:p class=\"text_p\"><xhtml:span class=\"text_edgespan\">&nbsp;&nbsp;&nbsp;&nbsp;</xhtml:span><xhtml:span class=\"text_word\">I&nbsp;</xhtml:span><xhtml:span class=\"text_word\">never&nbsp;</xhtml:span><xhtml:span class=\"text_coloredword\" style=\"color:#94ffb6\">hear&nbsp;</xhtml:span><xhtml:span class=\"text_word\">of&nbsp;</xhtml:span><xhtml:span class=\"text_coloredword\" style=\"color:#ff08b4\">prisons&nbsp;</xhtml:span><xhtml:span class=\"text_coloredword\" style=\"color:#c0a8ff\">broad&nbsp;</xhtml:span></xhtml:p><xhtml:p class=\"text_p\"><xhtml:span class=\"text_edgespan\">&nbsp;&nbsp;&nbsp;&nbsp;</xhtml:span><xhtml:span class=\"text_word\">By&nbsp;</xhtml:span><xhtml:span class=\"text_coloredword\" style=\"color:#f0ffa0\">soldiers&nbsp;</xhtml:span><xhtml:span class=\"text_coloredword\" style=\"color:#94ffb6\">battered&nbsp;</xhtml:span><xhtml:span class=\"text_word\">down&nbsp;</xhtml:span><xhtml:span class=\"text_word\">-&nbsp;</xhtml:span></xhtml:p><xhtml:p class=\"text_p\"><xhtml:span class=\"text_edgespan\">&nbsp;&nbsp;&nbsp;&nbsp;</xhtml:span><xhtml:span class=\"text_word\">But&nbsp;</xhtml:span><xhtml:span class=\"text_word\">I&nbsp;</xhtml:span><xhtml:span class=\"text_coloredword\" style=\"color:#94ffb6\">tug,&nbsp;</xhtml:span><xhtml:span class=\"text_coloredword\" style=\"color:#4cacc0\">childish,&nbsp;</xhtml:span><xhtml:span class=\"text_word\">at&nbsp;</xhtml:span><xhtml:span class=\"text_word\">my&nbsp;</xhtml:span><xhtml:span class=\"text_coloredword\" style=\"color:#dca4ff\">bars&nbsp;</xhtml:span><xhtml:span class=\"text_word\">-&nbsp;</xhtml:span></xhtml:p><xhtml:p class=\"text_p\"><xhtml:span class=\"text_edgespan\">&nbsp;&nbsp;&nbsp;&nbsp;</xhtml:span><xhtml:span class=\"text_word\">Only&nbsp;</xhtml:span><xhtml:span class=\"text_word\">to&nbsp;</xhtml:span><xhtml:span class=\"text_coloredword\" style=\"color:#94ffb6\">fail&nbsp;</xhtml:span><xhtml:span class=\"text_word\">again!&nbsp;</xhtml:span></xhtml:p><xhtml:p class=\"text_p\"><xhtml:span class=\"text_edgespan\">&nbsp;&nbsp;&nbsp;&nbsp;</xhtml:span><xhtml:span class=\"text_word\">&nbsp;</xhtml:span></xhtml:p>", "line_count": 9}}