{"document": {"filename": "1639_1932_0", "title": "1932_0", "lines_and_colors": [[["Of", "Paradise'", "existence"], {"1": "33", "2": "84"}], [["All", "we", "know"], {}], [["Is", "the", "uncertain", "certainty", "-"], {"2": "82", "3": "80"}], [["But", "it's", "vicinity,", "infer,"], {"1": "80", "2": "30", "3": "33"}], [["By", "it's", "Bisecting", "Messenger", "-"], {"1": "84", "2": "91", "3": "84"}], [[""], {}]], "full_text": "<xhtml:p class=\"text_p\"><xhtml:span class=\"text_edgespan\">&nbsp;</xhtml:span></xhtml:p><xhtml:p class=\"text_p\"><xhtml:span class=\"text_edgespan\">&nbsp;&nbsp;&nbsp;&nbsp;</xhtml:span><xhtml:span class=\"text_word\">Of&nbsp;</xhtml:span><xhtml:span class=\"text_coloredword\" style=\"color:#9cccff\">Paradise'&nbsp;</xhtml:span><xhtml:span class=\"text_coloredword\" style=\"color:#447cff\">existence&nbsp;</xhtml:span></xhtml:p><xhtml:p class=\"text_p\"><xhtml:span class=\"text_edgespan\">&nbsp;&nbsp;&nbsp;&nbsp;</xhtml:span><xhtml:span class=\"text_word\">All&nbsp;</xhtml:span><xhtml:span class=\"text_word\">we&nbsp;</xhtml:span><xhtml:span class=\"text_word\">know&nbsp;</xhtml:span></xhtml:p><xhtml:p class=\"text_p\"><xhtml:span class=\"text_edgespan\">&nbsp;&nbsp;&nbsp;&nbsp;</xhtml:span><xhtml:span class=\"text_word\">Is&nbsp;</xhtml:span><xhtml:span class=\"text_word\">the&nbsp;</xhtml:span><xhtml:span class=\"text_coloredword\" style=\"color:#1c30ff\">uncertain&nbsp;</xhtml:span><xhtml:span class=\"text_coloredword\" style=\"color:#38ff10\">certainty&nbsp;</xhtml:span><xhtml:span class=\"text_word\">-&nbsp;</xhtml:span></xhtml:p><xhtml:p class=\"text_p\"><xhtml:span class=\"text_edgespan\">&nbsp;&nbsp;&nbsp;&nbsp;</xhtml:span><xhtml:span class=\"text_word\">But&nbsp;</xhtml:span><xhtml:span class=\"text_coloredword\" style=\"color:#38ff10\">it's&nbsp;</xhtml:span><xhtml:span class=\"text_coloredword\" style=\"color:#7cff5c\">vicinity,&nbsp;</xhtml:span><xhtml:span class=\"text_coloredword\" style=\"color:#9cccff\">infer,&nbsp;</xhtml:span></xhtml:p><xhtml:p class=\"text_p\"><xhtml:span class=\"text_edgespan\">&nbsp;&nbsp;&nbsp;&nbsp;</xhtml:span><xhtml:span class=\"text_word\">By&nbsp;</xhtml:span><xhtml:span class=\"text_coloredword\" style=\"color:#447cff\">it's&nbsp;</xhtml:span><xhtml:span class=\"text_coloredword\" style=\"color:#c4c8ff\">Bisecting&nbsp;</xhtml:span><xhtml:span class=\"text_coloredword\" style=\"color:#447cff\">Messenger&nbsp;</xhtml:span><xhtml:span class=\"text_word\">-&nbsp;</xhtml:span></xhtml:p><xhtml:p class=\"text_p\"><xhtml:span class=\"text_edgespan\">&nbsp;&nbsp;&nbsp;&nbsp;</xhtml:span><xhtml:span class=\"text_word\">&nbsp;</xhtml:span></xhtml:p>", "line_count": 6}}