{"document": {"filename": "1853_1854_0", "title": "1854_0", "lines_and_colors": [[["A", "Rat", "surrendered", "here"], {"1": "20", "2": "84"}], [["A", "brief", "career", "of", "Cheer"], {"2": "96", "4": "96"}], [["And", "Fraud", "and", "Fear."], {"1": "53", "3": "61"}], [["Of", "Ignominy's", "due"], {"1": "86", "2": "61"}], [["Let", "all", "addicted", "to"], {"2": "86"}], [["Beware", "-"], {"0": "61"}], [["The", "most", "obliging", "Trap"], {"2": "96", "3": "37"}], [["It's", "tendency", "to", "snap"], {"0": "84", "1": "34", "3": "37"}], [["Cannot", "resist", "-"], {"1": "84"}], [["Temptation", "is", "the", "Friend"], {"0": "37", "3": "20"}], [["Repugnantly", "resigned"], {"0": "28", "1": "53"}], [["At", "last."], {}], [[""], {}]], "full_text": "<xhtml:p class=\"text_p\"><xhtml:span class=\"text_edgespan\">&nbsp;</xhtml:span></xhtml:p><xhtml:p class=\"text_p\"><xhtml:span class=\"text_edgespan\">&nbsp;&nbsp;&nbsp;&nbsp;</xhtml:span><xhtml:span class=\"text_word\">A&nbsp;</xhtml:span><xhtml:span class=\"text_coloredword\" style=\"color:#ff4614\">Rat&nbsp;</xhtml:span><xhtml:span class=\"text_coloredword\" style=\"color:#447cff\">surrendered&nbsp;</xhtml:span><xhtml:span class=\"text_word\">here&nbsp;</xhtml:span></xhtml:p><xhtml:p class=\"text_p\"><xhtml:span class=\"text_edgespan\">&nbsp;&nbsp;&nbsp;&nbsp;</xhtml:span><xhtml:span class=\"text_word\">A&nbsp;</xhtml:span><xhtml:span class=\"text_word\">brief&nbsp;</xhtml:span><xhtml:span class=\"text_coloredword\" style=\"color:#70e0ff\">career&nbsp;</xhtml:span><xhtml:span class=\"text_word\">of&nbsp;</xhtml:span><xhtml:span class=\"text_coloredword\" style=\"color:#70e0ff\">Cheer&nbsp;</xhtml:span></xhtml:p><xhtml:p class=\"text_p\"><xhtml:span class=\"text_edgespan\">&nbsp;&nbsp;&nbsp;&nbsp;</xhtml:span><xhtml:span class=\"text_word\">And&nbsp;</xhtml:span><xhtml:span class=\"text_coloredword\" style=\"color:#ac94ff\">Fraud&nbsp;</xhtml:span><xhtml:span class=\"text_word\">and&nbsp;</xhtml:span><xhtml:span class=\"text_coloredword\" style=\"color:#04c4ff\">Fear.&nbsp;</xhtml:span></xhtml:p><xhtml:p class=\"text_p\"><xhtml:span class=\"text_edgespan\">&nbsp;&nbsp;&nbsp;&nbsp;</xhtml:span><xhtml:span class=\"text_word\">Of&nbsp;</xhtml:span><xhtml:span class=\"text_coloredword\" style=\"color:#b8d058\">Ignominy's&nbsp;</xhtml:span><xhtml:span class=\"text_coloredword\" style=\"color:#04c4ff\">due&nbsp;</xhtml:span></xhtml:p><xhtml:p class=\"text_p\"><xhtml:span class=\"text_edgespan\">&nbsp;&nbsp;&nbsp;&nbsp;</xhtml:span><xhtml:span class=\"text_word\">Let&nbsp;</xhtml:span><xhtml:span class=\"text_word\">all&nbsp;</xhtml:span><xhtml:span class=\"text_coloredword\" style=\"color:#b8d058\">addicted&nbsp;</xhtml:span><xhtml:span class=\"text_word\">to&nbsp;</xhtml:span></xhtml:p><xhtml:p class=\"text_p\"><xhtml:span class=\"text_edgespan\">&nbsp;&nbsp;&nbsp;&nbsp;</xhtml:span><xhtml:span class=\"text_coloredword\" style=\"color:#04c4ff\">Beware&nbsp;</xhtml:span><xhtml:span class=\"text_word\">-&nbsp;</xhtml:span></xhtml:p><xhtml:p class=\"text_p\"><xhtml:span class=\"text_edgespan\">&nbsp;&nbsp;&nbsp;&nbsp;</xhtml:span><xhtml:span class=\"text_word\">The&nbsp;</xhtml:span><xhtml:span class=\"text_word\">most&nbsp;</xhtml:span><xhtml:span class=\"text_coloredword\" style=\"color:#70e0ff\">obliging&nbsp;</xhtml:span><xhtml:span class=\"text_coloredword\" style=\"color:#4840ff\">Trap&nbsp;</xhtml:span></xhtml:p><xhtml:p class=\"text_p\"><xhtml:span class=\"text_edgespan\">&nbsp;&nbsp;&nbsp;&nbsp;</xhtml:span><xhtml:span class=\"text_coloredword\" style=\"color:#447cff\">It's&nbsp;</xhtml:span><xhtml:span class=\"text_coloredword\" style=\"color:#10ff7a\">tendency&nbsp;</xhtml:span><xhtml:span class=\"text_word\">to&nbsp;</xhtml:span><xhtml:span class=\"text_coloredword\" style=\"color:#4840ff\">snap&nbsp;</xhtml:span></xhtml:p><xhtml:p class=\"text_p\"><xhtml:span class=\"text_edgespan\">&nbsp;&nbsp;&nbsp;&nbsp;</xhtml:span><xhtml:span class=\"text_word\">Cannot&nbsp;</xhtml:span><xhtml:span class=\"text_coloredword\" style=\"color:#447cff\">resist&nbsp;</xhtml:span><xhtml:span class=\"text_word\">-&nbsp;</xhtml:span></xhtml:p><xhtml:p class=\"text_p\"><xhtml:span class=\"text_edgespan\">&nbsp;&nbsp;&nbsp;&nbsp;</xhtml:span><xhtml:span class=\"text_coloredword\" style=\"color:#4840ff\">Temptation&nbsp;</xhtml:span><xhtml:span class=\"text_word\">is&nbsp;</xhtml:span><xhtml:span class=\"text_word\">the&nbsp;</xhtml:span><xhtml:span class=\"text_coloredword\" style=\"color:#ff4614\">Friend&nbsp;</xhtml:span></xhtml:p><xhtml:p class=\"text_p\"><xhtml:span class=\"text_edgespan\">&nbsp;&nbsp;&nbsp;&nbsp;</xhtml:span><xhtml:span class=\"text_coloredword\" style=\"color:#70c8ff\">Repugnantly&nbsp;</xhtml:span><xhtml:span class=\"text_coloredword\" style=\"color:#ac94ff\">resigned&nbsp;</xhtml:span></xhtml:p><xhtml:p class=\"text_p\"><xhtml:span class=\"text_edgespan\">&nbsp;&nbsp;&nbsp;&nbsp;</xhtml:span><xhtml:span class=\"text_word\">At&nbsp;</xhtml:span><xhtml:span class=\"text_word\">last.&nbsp;</xhtml:span></xhtml:p><xhtml:p class=\"text_p\"><xhtml:span class=\"text_edgespan\">&nbsp;&nbsp;&nbsp;&nbsp;</xhtml:span><xhtml:span class=\"text_word\">&nbsp;</xhtml:span></xhtml:p>", "line_count": 13}}