{"document": {"filename": "309_339_0", "title": "339_0", "lines_and_colors": [[["No", "Wilderness", "can", "be"], {"1": "23"}], [["Where", "this", "attendeth", "thee", "-"], {"2": "23", "3": "54"}], [["No", "Desert", "Noon", "-"], {"1": "23", "2": "23"}], [["No", "fear", "of", "frost", "to", "come"], {"1": "33", "3": "76"}], [["Haunt", "the", "perennial", "bloom", "-"], {"0": "33", "2": "76", "3": "76"}], [["But", "Certain", "June!"], {"2": "76"}], [[""], {}]], "full_text": "<xhtml:p class=\"text_p\"><xhtml:span class=\"text_edgespan\">&nbsp;</xhtml:span></xhtml:p><xhtml:p class=\"text_p\"><xhtml:span class=\"text_edgespan\">&nbsp;&nbsp;&nbsp;&nbsp;</xhtml:span><xhtml:span class=\"text_word\">No&nbsp;</xhtml:span><xhtml:span class=\"text_coloredword\" style=\"color:#84643c\">Wilderness&nbsp;</xhtml:span><xhtml:span class=\"text_word\">can&nbsp;</xhtml:span><xhtml:span class=\"text_word\">be&nbsp;</xhtml:span></xhtml:p><xhtml:p class=\"text_p\"><xhtml:span class=\"text_edgespan\">&nbsp;&nbsp;&nbsp;&nbsp;</xhtml:span><xhtml:span class=\"text_word\">Where&nbsp;</xhtml:span><xhtml:span class=\"text_word\">this&nbsp;</xhtml:span><xhtml:span class=\"text_coloredword\" style=\"color:#84643c\">attendeth&nbsp;</xhtml:span><xhtml:span class=\"text_coloredword\" style=\"color:#bcc0ff\">thee&nbsp;</xhtml:span><xhtml:span class=\"text_word\">-&nbsp;</xhtml:span></xhtml:p><xhtml:p class=\"text_p\"><xhtml:span class=\"text_edgespan\">&nbsp;&nbsp;&nbsp;&nbsp;</xhtml:span><xhtml:span class=\"text_word\">No&nbsp;</xhtml:span><xhtml:span class=\"text_coloredword\" style=\"color:#84643c\">Desert&nbsp;</xhtml:span><xhtml:span class=\"text_coloredword\" style=\"color:#84643c\">Noon&nbsp;</xhtml:span><xhtml:span class=\"text_word\">-&nbsp;</xhtml:span></xhtml:p><xhtml:p class=\"text_p\"><xhtml:span class=\"text_edgespan\">&nbsp;&nbsp;&nbsp;&nbsp;</xhtml:span><xhtml:span class=\"text_word\">No&nbsp;</xhtml:span><xhtml:span class=\"text_coloredword\" style=\"color:#9cccff\">fear&nbsp;</xhtml:span><xhtml:span class=\"text_word\">of&nbsp;</xhtml:span><xhtml:span class=\"text_coloredword\" style=\"color:#a06848\">frost&nbsp;</xhtml:span><xhtml:span class=\"text_word\">to&nbsp;</xhtml:span><xhtml:span class=\"text_word\">come&nbsp;</xhtml:span></xhtml:p><xhtml:p class=\"text_p\"><xhtml:span class=\"text_edgespan\">&nbsp;&nbsp;&nbsp;&nbsp;</xhtml:span><xhtml:span class=\"text_coloredword\" style=\"color:#9cccff\">Haunt&nbsp;</xhtml:span><xhtml:span class=\"text_word\">the&nbsp;</xhtml:span><xhtml:span class=\"text_coloredword\" style=\"color:#a06848\">perennial&nbsp;</xhtml:span><xhtml:span class=\"text_coloredword\" style=\"color:#a06848\">bloom&nbsp;</xhtml:span><xhtml:span class=\"text_word\">-&nbsp;</xhtml:span></xhtml:p><xhtml:p class=\"text_p\"><xhtml:span class=\"text_edgespan\">&nbsp;&nbsp;&nbsp;&nbsp;</xhtml:span><xhtml:span class=\"text_word\">But&nbsp;</xhtml:span><xhtml:span class=\"text_word\">Certain&nbsp;</xhtml:span><xhtml:span class=\"text_coloredword\" style=\"color:#a06848\">June!&nbsp;</xhtml:span></xhtml:p><xhtml:p class=\"text_p\"><xhtml:span class=\"text_edgespan\">&nbsp;&nbsp;&nbsp;&nbsp;</xhtml:span><xhtml:span class=\"text_word\">&nbsp;</xhtml:span></xhtml:p>", "line_count": 7}}