{"document": {"filename": "815_1619_0", "title": "1619_0", "lines_and_colors": [[["The", "pungent", "Atom", "in", "the", "Air"], {"1": "85", "2": "75", "5": "16"}], [["Admits", "of", "no", "debate", "-"], {"0": "16", "3": "76"}], [["All", "that", "is", "named", "of", "Summer", "Days"], {"3": "69", "5": "76", "6": "16"}], [["Relinquished", "our", "Estate", "-"], {"0": "16", "2": "85"}], [["For", "what", "Department", "of", "Delight"], {"2": "76", "4": "85"}], [["As", "positive", "are", "we"], {"1": "69"}], [["As", "Limit", "of", "Dominion"], {"1": "75", "3": "75"}], [["Or", "Dams", "-", "of", "Extasy", "-"], {"1": "75", "4": "10"}], [[""], {}]], "full_text": "<xhtml:p class=\"text_p\"><xhtml:span class=\"text_edgespan\">&nbsp;</xhtml:span></xhtml:p><xhtml:p class=\"text_p\"><xhtml:span class=\"text_edgespan\">&nbsp;&nbsp;&nbsp;&nbsp;</xhtml:span><xhtml:span class=\"text_word\">The&nbsp;</xhtml:span><xhtml:span class=\"text_coloredword\" style=\"color:#7074ff\">pungent&nbsp;</xhtml:span><xhtml:span class=\"text_coloredword\" style=\"color:#ac4cff\">Atom&nbsp;</xhtml:span><xhtml:span class=\"text_word\">in&nbsp;</xhtml:span><xhtml:span class=\"text_word\">the&nbsp;</xhtml:span><xhtml:span class=\"text_coloredword\" style=\"color:#44ff70\">Air&nbsp;</xhtml:span></xhtml:p><xhtml:p class=\"text_p\"><xhtml:span class=\"text_edgespan\">&nbsp;&nbsp;&nbsp;&nbsp;</xhtml:span><xhtml:span class=\"text_coloredword\" style=\"color:#44ff70\">Admits&nbsp;</xhtml:span><xhtml:span class=\"text_word\">of&nbsp;</xhtml:span><xhtml:span class=\"text_word\">no&nbsp;</xhtml:span><xhtml:span class=\"text_coloredword\" style=\"color:#a06848\">debate&nbsp;</xhtml:span><xhtml:span class=\"text_word\">-&nbsp;</xhtml:span></xhtml:p><xhtml:p class=\"text_p\"><xhtml:span class=\"text_edgespan\">&nbsp;&nbsp;&nbsp;&nbsp;</xhtml:span><xhtml:span class=\"text_word\">All&nbsp;</xhtml:span><xhtml:span class=\"text_word\">that&nbsp;</xhtml:span><xhtml:span class=\"text_word\">is&nbsp;</xhtml:span><xhtml:span class=\"text_coloredword\" style=\"color:#5868ff\">named&nbsp;</xhtml:span><xhtml:span class=\"text_word\">of&nbsp;</xhtml:span><xhtml:span class=\"text_coloredword\" style=\"color:#a06848\">Summer&nbsp;</xhtml:span><xhtml:span class=\"text_coloredword\" style=\"color:#44ff70\">Days&nbsp;</xhtml:span></xhtml:p><xhtml:p class=\"text_p\"><xhtml:span class=\"text_edgespan\">&nbsp;&nbsp;&nbsp;&nbsp;</xhtml:span><xhtml:span class=\"text_coloredword\" style=\"color:#44ff70\">Relinquished&nbsp;</xhtml:span><xhtml:span class=\"text_word\">our&nbsp;</xhtml:span><xhtml:span class=\"text_coloredword\" style=\"color:#7074ff\">Estate&nbsp;</xhtml:span><xhtml:span class=\"text_word\">-&nbsp;</xhtml:span></xhtml:p><xhtml:p class=\"text_p\"><xhtml:span class=\"text_edgespan\">&nbsp;&nbsp;&nbsp;&nbsp;</xhtml:span><xhtml:span class=\"text_word\">For&nbsp;</xhtml:span><xhtml:span class=\"text_word\">what&nbsp;</xhtml:span><xhtml:span class=\"text_coloredword\" style=\"color:#a06848\">Department&nbsp;</xhtml:span><xhtml:span class=\"text_word\">of&nbsp;</xhtml:span><xhtml:span class=\"text_coloredword\" style=\"color:#7074ff\">Delight&nbsp;</xhtml:span></xhtml:p><xhtml:p class=\"text_p\"><xhtml:span class=\"text_edgespan\">&nbsp;&nbsp;&nbsp;&nbsp;</xhtml:span><xhtml:span class=\"text_word\">As&nbsp;</xhtml:span><xhtml:span class=\"text_coloredword\" style=\"color:#5868ff\">positive&nbsp;</xhtml:span><xhtml:span class=\"text_word\">are&nbsp;</xhtml:span><xhtml:span class=\"text_word\">we&nbsp;</xhtml:span></xhtml:p><xhtml:p class=\"text_p\"><xhtml:span class=\"text_edgespan\">&nbsp;&nbsp;&nbsp;&nbsp;</xhtml:span><xhtml:span class=\"text_word\">As&nbsp;</xhtml:span><xhtml:span class=\"text_coloredword\" style=\"color:#ac4cff\">Limit&nbsp;</xhtml:span><xhtml:span class=\"text_word\">of&nbsp;</xhtml:span><xhtml:span class=\"text_coloredword\" style=\"color:#ac4cff\">Dominion&nbsp;</xhtml:span></xhtml:p><xhtml:p class=\"text_p\"><xhtml:span class=\"text_edgespan\">&nbsp;&nbsp;&nbsp;&nbsp;</xhtml:span><xhtml:span class=\"text_word\">Or&nbsp;</xhtml:span><xhtml:span class=\"text_coloredword\" style=\"color:#ac4cff\">Dams&nbsp;</xhtml:span><xhtml:span class=\"text_word\">-&nbsp;</xhtml:span><xhtml:span class=\"text_word\">of&nbsp;</xhtml:span><xhtml:span class=\"text_coloredword\" style=\"color:#7468ff\">Extasy&nbsp;</xhtml:span><xhtml:span class=\"text_word\">-&nbsp;</xhtml:span></xhtml:p><xhtml:p class=\"text_p\"><xhtml:span class=\"text_edgespan\">&nbsp;&nbsp;&nbsp;&nbsp;</xhtml:span><xhtml:span class=\"text_word\">&nbsp;</xhtml:span></xhtml:p>", "line_count": 9}}