{"document": {"filename": "862_1037_0", "title": "1037_0", "lines_and_colors": [[["It", "dropped", "so", "low", "-", "in", "my", "Regard", "-"], {"1": "18", "3": "89", "7": "18"}], [["I", "heard", "it", "hit", "the", "Ground", "-"], {"1": "89", "3": "26", "5": "18"}], [["And", "go", "to", "pieces", "on", "the", "Stones"], {"3": "28", "6": "18"}], [["At", "bottom", "of", "my", "mind", "-"], {"1": "89", "4": "25"}], [["Yet", "blamed", "the", "Fate", "that", "fractured", "-", "less"], {"1": "45", "3": "18", "5": "2"}], [["Than", "I", "reviled", "Myself,"], {"2": "18"}], [["For", "entertaining", "Plated", "Wares"], {"1": "94", "2": "28", "3": "45"}], [["Opon", "my", "Silver", "Shelf", "-"], {"0": "92", "2": "18", "3": "89"}], [[""], {}]], "full_text": "<xhtml:p class=\"text_p\"><xhtml:span class=\"text_edgespan\">&nbsp;</xhtml:span></xhtml:p><xhtml:p class=\"text_p\"><xhtml:span class=\"text_edgespan\">&nbsp;&nbsp;&nbsp;&nbsp;</xhtml:span><xhtml:span class=\"text_word\">It&nbsp;</xhtml:span><xhtml:span class=\"text_coloredword\" style=\"color:#b4ff94\">dropped&nbsp;</xhtml:span><xhtml:span class=\"text_word\">so&nbsp;</xhtml:span><xhtml:span class=\"text_coloredword\" style=\"color:#c88cff\">low&nbsp;</xhtml:span><xhtml:span class=\"text_word\">-&nbsp;</xhtml:span><xhtml:span class=\"text_word\">in&nbsp;</xhtml:span><xhtml:span class=\"text_word\">my&nbsp;</xhtml:span><xhtml:span class=\"text_coloredword\" style=\"color:#b4ff94\">Regard&nbsp;</xhtml:span><xhtml:span class=\"text_word\">-&nbsp;</xhtml:span></xhtml:p><xhtml:p class=\"text_p\"><xhtml:span class=\"text_edgespan\">&nbsp;&nbsp;&nbsp;&nbsp;</xhtml:span><xhtml:span class=\"text_word\">I&nbsp;</xhtml:span><xhtml:span class=\"text_coloredword\" style=\"color:#c88cff\">heard&nbsp;</xhtml:span><xhtml:span class=\"text_word\">it&nbsp;</xhtml:span><xhtml:span class=\"text_coloredword\" style=\"color:#d078ff\">hit&nbsp;</xhtml:span><xhtml:span class=\"text_word\">the&nbsp;</xhtml:span><xhtml:span class=\"text_coloredword\" style=\"color:#b4ff94\">Ground&nbsp;</xhtml:span><xhtml:span class=\"text_word\">-&nbsp;</xhtml:span></xhtml:p><xhtml:p class=\"text_p\"><xhtml:span class=\"text_edgespan\">&nbsp;&nbsp;&nbsp;&nbsp;</xhtml:span><xhtml:span class=\"text_word\">And&nbsp;</xhtml:span><xhtml:span class=\"text_word\">go&nbsp;</xhtml:span><xhtml:span class=\"text_word\">to&nbsp;</xhtml:span><xhtml:span class=\"text_coloredword\" style=\"color:#70c8ff\">pieces&nbsp;</xhtml:span><xhtml:span class=\"text_word\">on&nbsp;</xhtml:span><xhtml:span class=\"text_word\">the&nbsp;</xhtml:span><xhtml:span class=\"text_coloredword\" style=\"color:#b4ff94\">Stones&nbsp;</xhtml:span></xhtml:p><xhtml:p class=\"text_p\"><xhtml:span class=\"text_edgespan\">&nbsp;&nbsp;&nbsp;&nbsp;</xhtml:span><xhtml:span class=\"text_word\">At&nbsp;</xhtml:span><xhtml:span class=\"text_coloredword\" style=\"color:#c88cff\">bottom&nbsp;</xhtml:span><xhtml:span class=\"text_word\">of&nbsp;</xhtml:span><xhtml:span class=\"text_word\">my&nbsp;</xhtml:span><xhtml:span class=\"text_coloredword\" style=\"color:#ffc4a4\">mind&nbsp;</xhtml:span><xhtml:span class=\"text_word\">-&nbsp;</xhtml:span></xhtml:p><xhtml:p class=\"text_p\"><xhtml:span class=\"text_edgespan\">&nbsp;&nbsp;&nbsp;&nbsp;</xhtml:span><xhtml:span class=\"text_word\">Yet&nbsp;</xhtml:span><xhtml:span class=\"text_coloredword\" style=\"color:#34ccff\">blamed&nbsp;</xhtml:span><xhtml:span class=\"text_word\">the&nbsp;</xhtml:span><xhtml:span class=\"text_coloredword\" style=\"color:#b4ff94\">Fate&nbsp;</xhtml:span><xhtml:span class=\"text_word\">that&nbsp;</xhtml:span><xhtml:span class=\"text_coloredword\" style=\"color:#f0ffa0\">fractured&nbsp;</xhtml:span><xhtml:span class=\"text_word\">-&nbsp;</xhtml:span><xhtml:span class=\"text_word\">less&nbsp;</xhtml:span></xhtml:p><xhtml:p class=\"text_p\"><xhtml:span class=\"text_edgespan\">&nbsp;&nbsp;&nbsp;&nbsp;</xhtml:span><xhtml:span class=\"text_word\">Than&nbsp;</xhtml:span><xhtml:span class=\"text_word\">I&nbsp;</xhtml:span><xhtml:span class=\"text_coloredword\" style=\"color:#b4ff94\">reviled&nbsp;</xhtml:span><xhtml:span class=\"text_word\">Myself,&nbsp;</xhtml:span></xhtml:p><xhtml:p class=\"text_p\"><xhtml:span class=\"text_edgespan\">&nbsp;&nbsp;&nbsp;&nbsp;</xhtml:span><xhtml:span class=\"text_word\">For&nbsp;</xhtml:span><xhtml:span class=\"text_coloredword\" style=\"color:#705cff\">entertaining&nbsp;</xhtml:span><xhtml:span class=\"text_coloredword\" style=\"color:#70c8ff\">Plated&nbsp;</xhtml:span><xhtml:span class=\"text_coloredword\" style=\"color:#34ccff\">Wares&nbsp;</xhtml:span></xhtml:p><xhtml:p class=\"text_p\"><xhtml:span class=\"text_edgespan\">&nbsp;&nbsp;&nbsp;&nbsp;</xhtml:span><xhtml:span class=\"text_coloredword\" style=\"color:#c8e0b4\">Opon&nbsp;</xhtml:span><xhtml:span class=\"text_word\">my&nbsp;</xhtml:span><xhtml:span class=\"text_coloredword\" style=\"color:#b4ff94\">Silver&nbsp;</xhtml:span><xhtml:span class=\"text_coloredword\" style=\"color:#c88cff\">Shelf&nbsp;</xhtml:span><xhtml:span class=\"text_word\">-&nbsp;</xhtml:span></xhtml:p><xhtml:p class=\"text_p\"><xhtml:span class=\"text_edgespan\">&nbsp;&nbsp;&nbsp;&nbsp;</xhtml:span><xhtml:span class=\"text_word\">&nbsp;</xhtml:span></xhtml:p>", "line_count": 9}}